pyearth/__init__.py
pyearth/_basis.c
pyearth/_basis.pxd
pyearth/_basis.pyd
pyearth/_forward.c
pyearth/_forward.pxd
pyearth/_forward.pyd
pyearth/_knot_search.c
pyearth/_knot_search.pxd
pyearth/_knot_search.pyd
pyearth/_pruning.c
pyearth/_pruning.pxd
pyearth/_pruning.pyd
pyearth/_qr.c
pyearth/_qr.pxd
pyearth/_qr.pyd
pyearth/_record.c
pyearth/_record.pxd
pyearth/_record.pyd
pyearth/_types.c
pyearth/_types.pxd
pyearth/_types.pyd
pyearth/_util.c
pyearth/_util.pxd
pyearth/_util.pyd
pyearth/_version.py
pyearth/earth.py
pyearth/export.py
pyearth/test/__init__.py
pyearth/test/earth_linvars_regress.txt
pyearth/test/earth_regress.txt
pyearth/test/earth_regress_missing_data.txt
pyearth/test/earth_regress_smooth.txt
pyearth/test/forward_regress.txt
pyearth/test/test_data.csv
pyearth/test/test_earth.py
pyearth/test/test_export.py
pyearth/test/test_forward.py
pyearth/test/test_knot_search.py
pyearth/test/test_pruning.py
pyearth/test/test_qr.py
pyearth/test/test_util.py
pyearth/test/testing_utils.py
pyearth/test/basis/__init__.py
pyearth/test/basis/base.py
pyearth/test/basis/test_basis.py
pyearth/test/basis/test_constant.py
pyearth/test/basis/test_hinge.py
pyearth/test/basis/test_linear.py
pyearth/test/basis/test_missingness.py
pyearth/test/basis/test_smoothed_hinge.py
pyearth/test/record/__init__.py
pyearth/test/record/test_forward_pass.py
pyearth/test/record/test_pruning_pass.py
sklearn_contrib_py_earth-0.1.0.dist-info/DESCRIPTION.rst
sklearn_contrib_py_earth-0.1.0.dist-info/LICENSE.txt
sklearn_contrib_py_earth-0.1.0.dist-info/METADATA
sklearn_contrib_py_earth-0.1.0.dist-info/RECORD
sklearn_contrib_py_earth-0.1.0.dist-info/WHEEL
sklearn_contrib_py_earth-0.1.0.dist-info/metadata.json
sklearn_contrib_py_earth-0.1.0.dist-info/top_level.txt
