Metadata-Version: 2.0
Name: sklearn-contrib-py-earth
Version: 0.1.0
Summary: A Python implementation of Jerome Friedman's Multivariate Adaptive Regression Splines.
Home-page: UNKNOWN
Author: Jason Rudy
Author-email: jcrudy@gmail.com
License: LICENSE.txt
Download-URL: https://github.com/scikit-learn-contrib/py-earth/archive/0.1.tar.gz
Platform: UNKNOWN
Classifier: Intended Audience :: Developers
Classifier: Intended Audience :: Science/Research
Classifier: License :: OSI Approved :: BSD License
Classifier: Development Status :: 3 - Alpha
Classifier: Operating System :: MacOS
Classifier: Operating System :: Microsoft :: Windows
Classifier: Operating System :: POSIX
Classifier: Operating System :: Unix
Classifier: Programming Language :: Cython
Classifier: Programming Language :: Python
Classifier: Programming Language :: Python :: 2
Classifier: Programming Language :: Python :: 2.6
Classifier: Programming Language :: Python :: 2.7
Classifier: Programming Language :: Python :: 3
Classifier: Programming Language :: Python :: 3.4
Classifier: Programming Language :: Python :: 3.5
Classifier: Programming Language :: Python :: 3.6
Classifier: Topic :: Scientific/Engineering
Classifier: Topic :: Software Development
Requires-Dist: scipy (>=0.16)
Requires-Dist: scikit-learn (>=0.16)
Requires-Dist: six
Provides-Extra: all_tests
Requires-Dist: pandas; extra == 'all_tests'
Requires-Dist: statsmodels; extra == 'all_tests'
Requires-Dist: patsy; extra == 'all_tests'
Requires-Dist: sympy; extra == 'all_tests'
Provides-Extra: dev
Requires-Dist: cython; extra == 'dev'
Provides-Extra: docs
Requires-Dist: sphinx-gallery; extra == 'docs'
Provides-Extra: export
Requires-Dist: sympy; extra == 'export'
